zope/app/publisher/__init__.py
zope/app/publisher/configure.zcml
zope/app/publisher/fieldconverters.py
zope/app/publisher/fileresource.py
zope/app/publisher/ftesting.zcml
zope/app/publisher/http.zcml
zope/app/publisher/i18n.py
zope/app/publisher/meta.zcml
zope/app/publisher/pagetemplateresource.py
zope/app/publisher/testing.py
zope/app/publisher/browser/__init__.py
zope/app/publisher/browser/configure.zcml
zope/app/publisher/browser/directoryresource.py
zope/app/publisher/browser/fields.py
zope/app/publisher/browser/fileresource.py
zope/app/publisher/browser/i18nfileresource.py
zope/app/publisher/browser/i18nresourcemeta.py
zope/app/publisher/browser/icon.py
zope/app/publisher/browser/managementviewselector.py
zope/app/publisher/browser/menu.py
zope/app/publisher/browser/menumeta.py
zope/app/publisher/browser/meta.zcml
zope/app/publisher/browser/metaconfigure.py
zope/app/publisher/browser/metadirectives.py
zope/app/publisher/browser/pagetemplateresource.py
zope/app/publisher/browser/resource.py
zope/app/publisher/browser/resourcemeta.py
zope/app/publisher/browser/resources.py
zope/app/publisher/browser/viewmeta.py
zope/app/publisher/browser/vocabulary.py
zope/app/publisher/interfaces/__init__.py
zope/app/publisher/interfaces/browser.py
zope/app/publisher/interfaces/ftp.py
zope/app/publisher/interfaces/http.py
zope/app/publisher/interfaces/xmlrpc.py
zope/app/publisher/tests/__init__.py
zope/app/publisher/tests/test_bwc_imports.py
zope/app/publisher/tests/test_fieldconverters.py
zope/app/publisher/xmlrpc/README.rst
zope/app/publisher/xmlrpc/__init__.py
zope/app/publisher/xmlrpc/configure.zcml
zope/app/publisher/xmlrpc/meta.zcml
zope/app/publisher/xmlrpc/metaconfigure.py
zope/app/publisher/xmlrpc/metadirectives.py
zope/app/publisher/xmlrpc/testing.py
zope/app/publisher/xmlrpc/tests/__init__.py
zope/app/publisher/xmlrpc/tests/test.pt
zope/app/publisher/xmlrpc/tests/test_directives.py
zope/app/publisher/xmlrpc/tests/test_functional.py
zope_app_publisher-6.0.dist-info/licenses/LICENSE.txt
zope_app_publisher-6.0.dist-info/METADATA
zope_app_publisher-6.0.dist-info/WHEEL
zope_app_publisher-6.0.dist-info/top_level.txt
zope_app_publisher-6.0.dist-info/RECORD
