Metadata-Version: 2.4
Name: zope.app.publisher
Version: 6.0
Summary: Implementations and means for configuration of Zope 3-style views and resources.
Home-page: https://github.com/zopefoundation/zope.app.publisher/
Author: Zope Foundation and Contributors
Author-email: zope-dev@zope.dev
License: ZPL-2.1
Classifier: Development Status :: 5 - Production/Stable
Classifier: Environment :: Web Environment
Classifier: Intended Audience :: Developers
Classifier: License :: OSI Approved :: Zope Public License
Classifier: Programming Language :: Python
Classifier: Programming Language :: Python :: 3
Classifier: Programming Language :: Python :: 3.9
Classifier: Programming Language :: Python :: 3.10
Classifier: Programming Language :: Python :: 3.11
Classifier: Programming Language :: Python :: 3.12
Classifier: Programming Language :: Python :: 3.13
Classifier: Programming Language :: Python :: Implementation :: CPython
Classifier: Programming Language :: Python :: Implementation :: PyPy
Classifier: Natural Language :: English
Classifier: Operating System :: OS Independent
Classifier: Topic :: Internet :: WWW/HTTP
Classifier: Framework :: Zope :: 3
Requires-Python: >=3.9
License-File: LICENSE.txt
Requires-Dist: setuptools
Requires-Dist: zope.browsermenu
Requires-Dist: zope.browserpage
Requires-Dist: zope.browserresource
Requires-Dist: zope.component
Requires-Dist: zope.configuration
Requires-Dist: zope.datetime
Requires-Dist: zope.interface
Requires-Dist: zope.location
Requires-Dist: zope.ptresource
Requires-Dist: zope.publisher>=3.12
Requires-Dist: zope.schema
Requires-Dist: zope.security
Requires-Dist: zope.componentvocabulary
Provides-Extra: test
Requires-Dist: zope.app.appsetup; extra == "test"
Requires-Dist: zope.app.authentication; extra == "test"
Requires-Dist: zope.app.basicskin>=4.0.0; extra == "test"
Requires-Dist: zope.app.container>=4.0.0; extra == "test"
Requires-Dist: zope.app.form>=5.0.0; extra == "test"
Requires-Dist: zope.app.publisher; extra == "test"
Requires-Dist: zope.app.publication; extra == "test"
Requires-Dist: zope.app.rotterdam>=4.0.0; extra == "test"
Requires-Dist: zope.app.schema>=4.0.0; extra == "test"
Requires-Dist: zope.app.wsgi; extra == "test"
Requires-Dist: zope.browserpage; extra == "test"
Requires-Dist: zope.browserresource; extra == "test"
Requires-Dist: zope.container; extra == "test"
Requires-Dist: zope.deferredimport; extra == "test"
Requires-Dist: zope.formlib; extra == "test"
Requires-Dist: zope.login; extra == "test"
Requires-Dist: zope.principalannotation; extra == "test"
Requires-Dist: zope.principalregistry; extra == "test"
Requires-Dist: zope.publisher; extra == "test"
Requires-Dist: zope.securitypolicy; extra == "test"
Requires-Dist: zope.testbrowser>=5.2; extra == "test"
Requires-Dist: zope.testing; extra == "test"
Requires-Dist: zope.testrunner>=6.4; extra == "test"
Requires-Dist: zope.traversing>=4.1.0; extra == "test"
Requires-Dist: webtest; extra == "test"
Provides-Extra: testing
Requires-Dist: zope.app.wsgi; extra == "testing"
Dynamic: author
Dynamic: author-email
Dynamic: classifier
Dynamic: description
Dynamic: home-page
Dynamic: license
Dynamic: license-file
Dynamic: provides-extra
Dynamic: requires-dist
Dynamic: requires-python
Dynamic: summary
